haraka/__init__.py
haraka/PyFast/Runtime.py
haraka/PyFast/__init__.py
haraka/PyFast/core/__init__.py
haraka/PyFast/core/interfaces.py
haraka/art/__init__.py
haraka/art/create.py
haraka/art/ascii/__init__.py
haraka/art/ascii/assets.py
haraka/art/ascii/frame/__init__.py
haraka/art/ascii/frame/border.py
haraka/art/ascii/frame/framer.py
haraka/art/ascii/frame/width_utils.py
haraka/post_gen/__init__.py
haraka/post_gen/runner.py
haraka/post_gen/config/__init__.py
haraka/post_gen/config/config.py
haraka/post_gen/resources/__init__.py
haraka/post_gen/resources/assets.py
haraka/post_gen/service/__init__.py
haraka/post_gen/service/command.py
haraka/post_gen/service/fileOps/__init__.py
haraka/post_gen/service/fileOps/files.py
haraka/post_gen/service/fileOps/purge.py
haraka/post_gen/service/gitOps/__init__.py
haraka/post_gen/service/gitOps/gitops.py
haraka/utils/__init__.py
haraka/utils/common/__init__.py
haraka/utils/common/utils.py
haraka/utils/logging/__init__.py
haraka/utils/logging/log_util.py
haraka/utils/manifests/GoUltraFast.yml
haraka/utils/manifests/JavaFein.yml
haraka/utils/manifests/PyFast.yml
haraka/utils/manifests/go-grpc-gateway-buf.yml
haraka-0.2.62.dist-info/METADATA
haraka-0.2.62.dist-info/WHEEL
haraka-0.2.62.dist-info/top_level.txt
haraka-0.2.62.dist-info/RECORD
