Metadata-Version: 2.4
Name: haraka
Version: 0.2.62
Summary: Reusable post-generation helper for Cookiecutter micro-service templates
Author-email: Will Burks <will@example.com>
License: MIT
Project-URL: Homepage, https://github.com/wjb-dev/comet-postgen
Project-URL: Source, https://github.com/wjb-dev/comet-postgen
Classifier: Programming Language :: Python :: 3
Classifier: License :: OSI Approved :: MIT License
Classifier: Intended Audience :: Developers
Classifier: Topic :: Software Development :: Build Tools
Requires-Python: >=3.9
Requires-Dist: pathspec==0.10.3
Requires-Dist: PyYAML==6.0.1
Requires-Dist: wcwidth==0.2.5
Requires-Dist: fastapi==0.115.14
Provides-Extra: gen
Requires-Dist: pathspec==0.10.3; extra == "gen"
Requires-Dist: PyYAML==6.0.1; extra == "gen"
Requires-Dist: wcwidth==0.2.5; extra == "gen"
Provides-Extra: pyfast
Requires-Dist: fastapi==0.115.14; extra == "pyfast"
